Metadata-Version: 1.1
Name: mk.recipe.modwsgi
Version: 0.1
Summary: WSGI from buildout
Home-page: https://github.com/k4ml/mk.recipe.modwsgi
Author: Kamal Mustafa
Author-email: kamal.mustafa@gmail.com
License: ZPL
Keywords: wsgi buildout
Platform: UNKNOWN
Classifier: Development Status :: 3 - Alpha
Classifier: Framework :: Buildout :: Recipe
Classifier: Intended Audience :: Developers
Classifier: Intended Audience :: System Administrators
Classifier: License :: OSI Approved :: Zope Public License
Classifier: Programming Language :: Python :: 2
Classifier: Programming Language :: Python :: 2.4
Classifier: Programming Language :: Python :: 2.5
Classifier: Programming Language :: Python :: 2.6
Classifier: Programming Language :: Python :: 2.7
Classifier: Programming Language :: Python :: 3
